AlteraClock/SwitchesManager.v
module ButtonInterpreter(
    input button_i,
    input clk_i,
    input nreset_i,
    
    output pressed_o
    );

    reg [1:0] state;

    always @(negedge clk_i or negedge nreset_i) begin
        if (~nreset_i) state <= 2'b00;
        else if (~button_i) 
            case (state)
                2'b00: state <= 2'b01;
                2'b01: state <= 2'b10;
                2'b10: state <= 2'b10;
                default: state <= 2'b00;
            endcase
        else state <= 2'b00;
    end

    assign pressed_o = (state == 2'b01);

endmodule

module SwitchesManager(
    input key1_i,
    input key2_i,
    input key3_i,
    input set_switch_i,

    input clockmode_i,
    input stopwatchmode_i,
    input timermode_i,
    input clk_i,
    input nreset_i,
    
    output clock_set_run_switch_o, // set if 1, run if 0
    output clock_up_o, // key1
    output clock_down_o,  // key2
    output clock_setmode_o, // key3 set mode (sec, min, hr ) toggle
    
    // no output for switch, key1 for stopwatch
    output stopwatch_reset_o, // key2
    output stopwatch_runpause_o, // key3, run/pause toggle
    
    output timer_set_runorpause_switch_o, // set if 1, run or pause if 0
    output timer_up_o, // key1
    output timer_down_reset_o, // key2
    output timer_setmode_runpause_o // key3, set mode (sec, min, hr) toggle or run/pause toggle
    );

    wire [3:0] temp_outputs; // [0] for the switch, [1], [2], [3] for key1, key2, key3

    assign temp_outputs[0] = set_switch_i;

    ButtonInterpreter Key1Interpreter(
        .button_i(key1_i),
        .clk_i(clk_i),
        .nreset_i(nreset_i),
        .pressed_o(temp_outputs[1])
    );

    ButtonInterpreter Key2Interpreter(
        .button_i(key2_i),
        .clk_i(clk_i),
        .nreset_i(nreset_i),
        .pressed_o(temp_outputs[2])
    );

    ButtonInterpreter Key3Interpreter(
        .button_i(key3_i),
        .clk_i(clk_i),
        .nreset_i(nreset_i),
        .pressed_o(temp_outputs[3])
    );

    assign {clock_setmode_o, clock_down_o, clock_up_o, clock_set_run_switch_o} = {4{clockmode_i}} & temp_outputs;
    //      key3             key2          key1,       switch
    assign {stopwatch_runpause_o, stopwatch_reset_o} = {2{stopwatchmode_i}} & temp_outputs[3:2];
    //      key3                  key2
    assign {timer_setmode_runpause_o, timer_down_reset_o, timer_up_o, timer_set_runorpause_switch_o} = {4{timermode_i}} & temp_outputs;
    //      key3                      key2                key1        switch


endmodule

AlteraClock/tb_SwitchesManager.v
`timescale 1ns/1ns
`include "AlteraClock/SwitchesManager.v"

module tb_SwitchesManager();

    reg tb_key1;
    reg tb_key2;
    reg tb_key3;
    reg tb_set_switch;

    reg tb_clockmode;
    reg tb_stopwatchmode;
    reg tb_timermode;
    reg tb_clk;
    reg tb_nreset;
    
    wire tb_clock_set_run_switch; // set if 1, run if 0
    wire tb_clock_up; // key1
    wire tb_clock_down;  // key2
    wire tb_clock_setmode; // key3 set mode (sec, min, hr ) toggle
    
    wire tb_stopwatch_reset; // key2
    wire tb_stopwatch_runpause; // key3, run/pause toggle
    
    wire tb_timer_set_runorpause_switch; // set if 1, run or pause if 0
    wire tb_timer_up; // key1
    wire tb_timer_down_reset; // key2
    wire tb_timer_setmode_runpause; // key3, set mode (sec, min, hr) toggle or run/pause toggle

    SwitchesManager TestManager(
        .key1_i(tb_key1),
        .key2_i(tb_key2),
        .key3_i(tb_key3),
        .set_switch_i(tb_set_switch),

        .clockmode_i(tb_clockmode),
        .stopwatchmode_i(tb_stopwatchmode),
        .timermode_i(tb_timermode),
        .clk_i(tb_clk),
        .nreset_i(tb_nreset),
        
        .clock_set_run_switch_o(tb_clock_set_run_switch), 
        .clock_up_o(tb_clock_up), 
        .clock_down_o(tb_clock_down),  
        .clock_setmode_o(tb_clock_setmode), 
        
        .stopwatch_reset_o(tb_stopwatch_reset),
        .stopwatch_runpause_o(tb_stopwatch_runpause), 
        
        .timer_set_runorpause_switch_o(tb_timer_set_runorpause_switch), 
        .timer_up_o(tb_timer_up), 
        .timer_down_reset_o(tb_timer_down_reset), 
        .timer_setmode_runpause_o(tb_timer_setmode_runpause)
    );

    always #10 tb_clk <= ~tb_clk;

    initial begin
        $dumpfile("AlteraClock/BuildFiles/tb_SwitchesManager.vcd");
        $dumpvars(0, tb_SwitchesManager);

        tb_key1 = 0;
        tb_key2 = 0;
        tb_key3 = 0;
        tb_set_switch = 0;

        tb_clockmode = 0;
        tb_stopwatchmode = 0;
        tb_timermode = 0;
        tb_clk = 0;
        tb_nreset = 0;

        #2
        tb_nreset = 1;

        for (integer i = 0; i < 18; i = i + 1) begin
            #50;
            {tb_key1, tb_key2, tb_key3, tb_set_switch} = {tb_key1, tb_key2, tb_key3, tb_set_switch} + 1;
        end
        
        tb_key1 = 0;
        tb_key2 = 0;
        tb_key3 = 0;
        tb_set_switch = 0;
        tb_clockmode = 1;
        tb_stopwatchmode = 0;
        tb_timermode = 0;
        for (integer i = 0; i < 18; i = i + 1) begin
            #50;
            {tb_key1, tb_key2, tb_key3, tb_set_switch} = {tb_key1, tb_key2, tb_key3, tb_set_switch} + 1;
        end

        tb_key1 = 0;
        tb_key2 = 0;
        tb_key3 = 0;
        tb_set_switch = 0;
        tb_clockmode = 0;
        tb_stopwatchmode = 1;
        tb_timermode = 0;
        for (integer i = 0; i < 18; i = i + 1) begin
            #50;
            {tb_key1, tb_key2, tb_key3, tb_set_switch} = {tb_key1, tb_key2, tb_key3, tb_set_switch} + 1;
        end

        tb_key1 = 0;
        tb_key2 = 0;
        tb_key3 = 0;
        tb_set_switch = 0;
        tb_clockmode = 0;
        tb_stopwatchmode = 0;
        tb_timermode = 1;
        for (integer i = 0; i < 18; i = i + 1) begin
            #50;
            {tb_key1, tb_key2, tb_key3, tb_set_switch} = {tb_key1, tb_key2, tb_key3, tb_set_switch} + 1;
        end
        $finish;
    end
endmodule

AlteraClock/BuildFiles/tb_SwitchesManager.vcd
$date
	Tue Apr 16 16:58:54 2024
$end
$version
	Icarus Verilog
$end
$timescale
	1ns
$end
$scope module tb_SwitchesManager $end
$var wire 1 ! tb_timer_up $end
$var wire 1 " tb_timer_setmode_runpause $end
$var wire 1 # tb_timer_set_runorpause_switch $end
$var wire 1 $ tb_timer_down_reset $end
$var wire 1 % tb_stopwatch_runpause $end
$var wire 1 & tb_stopwatch_reset $end
$var wire 1 ' tb_clock_up $end
$var wire 1 ( tb_clock_setmode $end
$var wire 1 ) tb_clock_set_run_switch $end
$var wire 1 * tb_clock_down $end
$var reg 1 + tb_clk $end
$var reg 1 , tb_clockmode $end
$var reg 1 - tb_key1 $end
$var reg 1 . tb_key2 $end
$var reg 1 / tb_key3 $end
$var reg 1 0 tb_nreset $end
$var reg 1 1 tb_set_switch $end
$var reg 1 2 tb_stopwatchmode $end
$var reg 1 3 tb_timermode $end
$scope module TestManager $end
$var wire 1 + clk_i $end
$var wire 1 , clockmode_i $end
$var wire 1 - key1_i $end
$var wire 1 . key2_i $end
$var wire 1 / key3_i $end
$var wire 1 0 nreset_i $end
$var wire 1 1 set_switch_i $end
$var wire 1 2 stopwatchmode_i $end
$var wire 1 3 timermode_i $end
$var wire 1 ! timer_up_o $end
$var wire 1 " timer_setmode_runpause_o $end
$var wire 1 # timer_set_runorpause_switch_o $end
$var wire 1 $ timer_down_reset_o $end
$var wire 4 4 temp_outputs [3:0] $end
$var wire 1 % stopwatch_runpause_o $end
$var wire 1 & stopwatch_reset_o $end
$var wire 1 ' clock_up_o $end
$var wire 1 ( clock_setmode_o $end
$var wire 1 ) clock_set_run_switch_o $end
$var wire 1 * clock_down_o $end
$scope module Key1Interpreter $end
$var wire 1 - button_i $end
$var wire 1 + clk_i $end
$var wire 1 0 nreset_i $end
$var wire 1 5 pressed_o $end
$var reg 2 6 state [1:0] $end
$upscope $end
$scope module Key2Interpreter $end
$var wire 1 . button_i $end
$var wire 1 + clk_i $end
$var wire 1 0 nreset_i $end
$var wire 1 7 pressed_o $end
$var reg 2 8 state [1:0] $end
$upscope $end
$scope module Key3Interpreter $end
$var wire 1 / button_i $end
$var wire 1 + clk_i $end
$var wire 1 0 nreset_i $end
$var wire 1 9 pressed_o $end
$var reg 2 : state [1:0] $end
$upscope $end
$upscope $end
$scope begin $ivl_for_loop0 $end
$var integer 32 ; i [31:0] $end
$upscope $end
$scope begin $ivl_for_loop1 $end
$var integer 32 < i [31:0] $end
$upscope $end
$scope begin $ivl_for_loop2 $end
$var integer 32 = i [31:0] $end
$upscope $end
$scope begin $ivl_for_loop3 $end
$var integer 32 > i [31:0] $end
$upscope $end
$upscope $end
$enddefinitions $end
$comment Show the parameter values. $end
$dumpall
$end
#0
$dumpvars
bx >
bx =
bx <
bx ;
b0 :
09
b0 8
07
b0 6
05
b0 4
03
02
01
00
0/
0.
0-
0,
0+
0*
0)
0(
0'
0&
0%
0$
0#
0"
0!
$end
#2
b0 ;
10
#10
1+
#20
19
b1 :
17
b1 8
b1110 4
15
b1 6
0+
#30
1+
#40
05
b10 6
07
b10 8
b0 4
09
b10 :
0+
#50
1+
#52
b1 ;
b1 4
11
#60
0+
#70
1+
#80
0+
#90
1+
#100
0+
#102
b10 ;
1/
b0 4
01
#110
1+
#120
b0 :
0+
#130
1+
#140
0+
#150
1+
#152
b11 ;
b1 4
11
#160
0+
#170
1+
#180
0+
#190
1+
#200
0+
#202
b100 ;
1.
0/
b0 4
01
#210
1+
#220
b1000 4
19
b1 :
b0 8
0+
#230
1+
#240
b0 4
09
b10 :
0+
#250
1+
#252
b101 ;
b1 4
11
#260
0+
#270
1+
#280
0+
#290
1+
#300
0+
#302
b110 ;
1/
b0 4
01
#310
1+
#320
b0 :
0+
#330
1+
#340
0+
#350
1+
#352
b111 ;
b1 4
11
#360
0+
#370
1+
#380
0+
#390
1+
#400
0+
#402
b1000 ;
1-
0.
0/
b0 4
01
#410
1+
#420
19
b1 :
b1100 4
17
b1 8
b0 6
0+
#430
1+
#440
07
b10 8
b0 4
09
b10 :
0+
#450
1+
#452
b1001 ;
b1 4
11
#460
0+
#470
1+
#480
0+
#490
1+
#500
0+
#502
b1010 ;
1/
b0 4
01
#510
1+
#520
b0 :
0+
#530
1+
#540
0+
#550
1+
#552
b1011 ;
b1 4
11
#560
0+
#570
1+
#580
0+
#590
1+
#600
0+
#602
b1100 ;
1.
0/
b0 4
01
#610
1+
#620
b1000 4
19
b1 :
b0 8
0+
#630
1+
#640
b0 4
09
b10 :
0+
#650
1+
#652
b1101 ;
b1 4
11
#660
0+
#670
1+
#680
0+
#690
1+
#700
0+
#702
b1110 ;
1/
b0 4
01
#710
1+
#720
b0 :
0+
#730
1+
#740
0+
#750
1+
#752
b1111 ;
b1 4
11
#760
0+
#770
1+
#780
0+
#790
1+
#800
0+
#802
b10000 ;
0-
0.
0/
b0 4
01
#810
1+
#820
19
b1 :
17
b1 8
b1110 4
15
b1 6
0+
#830
1+
#840
05
b10 6
07
b10 8
b0 4
09
b10 :
0+
#850
1+
#852
b10001 ;
b1 4
11
#860
0+
#870
1+
#880
0+
#890
1+
#900
0+
#902
b0 <
1,
b10010 ;
0/
b0 4
01
#910
1+
#920
0+
#930
1+
#940
0+
#950
1+
#952
1)
b1 <
b1 4
11
#960
0+
#970
1+
#980
0+
#990
1+
#1000
0+
#1002
0)
b10 <
1/
b0 4
01
#1010
1+
#1020
b0 :
0+
#1030
1+
#1040
0+
#1050
1+
#1052
1)
b11 <
b1 4
11
#1060
0+
#1070
1+
#1080
0+
#1090
1+
#1100
0+
#1102
0)
b100 <
1.
0/
b0 4
01
#1110
1+
#1120
1(
b0 8
b1000 4
19
b1 :
0+
#1130
1+
#1140
0(
b0 4
09
b10 :
0+
#1150
1+
#1152
1)
b101 <
b1 4
11
#1160
0+
#1170
1+
#1180
0+
#1190
1+
#1200
0+
#1202
0)
b110 <
1/
b0 4
01
#1210
1+
#1220
b0 :
0+
#1230
1+
#1240
0+
#1250
1+
#1252
1)
b111 <
b1 4
11
#1260
0+
#1270
1+
#1280
0+
#1290
1+
#1300
0+
#1302
0)
b1000 <
1-
0.
0/
b0 4
01
#1310
1+
#1320
1(
1*
b0 6
17
b1 8
b1100 4
19
b1 :
0+
#1330
1+
#1340
0(
0*
09
b10 :
b0 4
07
b10 8
0+
#1350
1+
#1352
1)
b1001 <
b1 4
11
#1360
0+
#1370
1+
#1380
0+
#1390
1+
#1400
0+
#1402
0)
b1010 <
1/
b0 4
01
#1410
1+
#1420
b0 :
0+
#1430
1+
#1440
0+
#1450
1+
#1452
1)
b1011 <
b1 4
11
#1460
0+
#1470
1+
#1480
0+
#1490
1+
#1500
0+
#1502
0)
b1100 <
1.
0/
b0 4
01
#1510
1+
#1520
1(
b0 8
b1000 4
19
b1 :
0+
#1530
1+
#1540
0(
b0 4
09
b10 :
0+
#1550
1+
#1552
1)
b1101 <
b1 4
11
#1560
0+
#1570
1+
#1580
0+
#1590
1+
#1600
0+
#1602
0)
b1110 <
1/
b0 4
01
#1610
1+
#1620
b0 :
0+
#1630
1+
#1640
0+
#1650
1+
#1652
1)
b1111 <
b1 4
11
#1660
0+
#1670
1+
#1680
0+
#1690
1+
#1700
0+
#1702
0)
b10000 <
0-
0.
0/
b0 4
01
#1710
1+
#1720
1(
1*
1'
15
b1 6
17
b1 8
b1110 4
19
b1 :
0+
#1730
1+
#1740
0(
0*
0'
09
b10 :
07
b10 8
b0 4
05
b10 6
0+
#1750
1+
#1752
1)
b10001 <
b1 4
11
#1760
0+
#1770
1+
#1780
0+
#1790
1+
#1800
0+
#1802
0)
b0 =
12
0,
b10010 <
0/
b0 4
01
#1810
1+
#1820
0+
#1830
1+
#1840
0+
#1850
1+
#1852
b1 =
b1 4
11
#1860
0+
#1870
1+
#1880
0+
#1890
1+
#1900
0+
#1902
b10 =
1/
b0 4
01
#1910
1+
#1920
b0 :
0+
#1930
1+
#1940
0+
#1950
1+
#1952
b11 =
b1 4
11
#1960
0+
#1970
1+
#1980
0+
#1990
1+
#2000
0+
#2002
b100 =
1.
0/
b0 4
01
#2010
1+
#2020
1%
b1000 4
19
b1 :
b0 8
0+
#2030
1+
#2040
0%
b0 4
09
b10 :
0+
#2050
1+
#2052
b101 =
b1 4
11
#2060
0+
#2070
1+
#2080
0+
#2090
1+
#2100
0+
#2102
b110 =
1/
b0 4
01
#2110
1+
#2120
b0 :
0+
#2130
1+
#2140
0+
#2150
1+
#2152
b111 =
b1 4
11
#2160
0+
#2170
1+
#2180
0+
#2190
1+
#2200
0+
#2202
b1000 =
1-
0.
0/
b0 4
01
#2210
1+
#2220
1%
1&
19
b1 :
b1100 4
17
b1 8
b0 6
0+
#2230
1+
#2240
0%
0&
07
b10 8
b0 4
09
b10 :
0+
#2250
1+
#2252
b1001 =
b1 4
11
#2260
0+
#2270
1+
#2280
0+
#2290
1+
#2300
0+
#2302
b1010 =
1/
b0 4
01
#2310
1+
#2320
b0 :
0+
#2330
1+
#2340
0+
#2350
1+
#2352
b1011 =
b1 4
11
#2360
0+
#2370
1+
#2380
0+
#2390
1+
#2400
0+
#2402
b1100 =
1.
0/
b0 4
01
#2410
1+
#2420
1%
b1000 4
19
b1 :
b0 8
0+
#2430
1+
#2440
0%
b0 4
09
b10 :
0+
#2450
1+
#2452
b1101 =
b1 4
11
#2460
0+
#2470
1+
#2480
0+
#2490
1+
#2500
0+
#2502
b1110 =
1/
b0 4
01
#2510
1+
#2520
b0 :
0+
#2530
1+
#2540
0+
#2550
1+
#2552
b1111 =
b1 4
11
#2560
0+
#2570
1+
#2580
0+
#2590
1+
#2600
0+
#2602
b10000 =
0-
0.
0/
b0 4
01
#2610
1+
#2620
1%
1&
19
b1 :
17
b1 8
b1110 4
15
b1 6
0+
#2630
1+
#2640
0%
0&
05
b10 6
07
b10 8
b0 4
09
b10 :
0+
#2650
1+
#2652
b10001 =
b1 4
11
#2660
0+
#2670
1+
#2680
0+
#2690
1+
#2700
0+
#2702
b0 >
13
02
b10010 =
0/
b0 4
01
#2710
1+
#2720
0+
#2730
1+
#2740
0+
#2750
1+
#2752
1#
b1 >
b1 4
11
#2760
0+
#2770
1+
#2780
0+
#2790
1+
#2800
0+
#2802
0#
b10 >
1/
b0 4
01
#2810
1+
#2820
b0 :
0+
#2830
1+
#2840
0+
#2850
1+
#2852
1#
b11 >
b1 4
11
#2860
0+
#2870
1+
#2880
0+
#2890
1+
#2900
0+
#2902
0#
b100 >
1.
0/
b0 4
01
#2910
1+
#2920
1"
b0 8
b1000 4
19
b1 :
0+
#2930
1+
#2940
0"
b0 4
09
b10 :
0+
#2950
1+
#2952
1#
b101 >
b1 4
11
#2960
0+
#2970
1+
#2980
0+
#2990
1+
#3000
0+
#3002
0#
b110 >
1/
b0 4
01
#3010
1+
#3020
b0 :
0+
#3030
1+
#3040
0+
#3050
1+
#3052
1#
b111 >
b1 4
11
#3060
0+
#3070
1+
#3080
0+
#3090
1+
#3100
0+
#3102
0#
b1000 >
1-
0.
0/
b0 4
01
#3110
1+
#3120
1"
1$
b0 6
17
b1 8
b1100 4
19
b1 :
0+
#3130
1+
#3140
0"
0$
09
b10 :
b0 4
07
b10 8
0+
#3150
1+
#3152
1#
b1001 >
b1 4
11
#3160
0+
#3170
1+
#3180
0+
#3190
1+
#3200
0+
#3202
0#
b1010 >
1/
b0 4
01
#3210
1+
#3220
b0 :
0+
#3230
1+
#3240
0+
#3250
1+
#3252
1#
b1011 >
b1 4
11
#3260
0+
#3270
1+
#3280
0+
#3290
1+
#3300
0+
#3302
0#
b1100 >
1.
0/
b0 4
01
#3310
1+
#3320
1"
b0 8
b1000 4
19
b1 :
0+
#3330
1+
#3340
0"
b0 4
09
b10 :
0+
#3350
1+
#3352
1#
b1101 >
b1 4
11
#3360
0+
#3370
1+
#3380
0+
#3390
1+
#3400
0+
#3402
0#
b1110 >
1/
b0 4
01
#3410
1+
#3420
b0 :
0+
#3430
1+
#3440
0+
#3450
1+
#3452
1#
b1111 >
b1 4
11
#3460
0+
#3470
1+
#3480
0+
#3490
1+
#3500
0+
#3502
0#
b10000 >
0-
0.
0/
b0 4
01
#3510
1+
#3520
1"
1$
1!
15
b1 6
17
b1 8
b1110 4
19
b1 :
0+
#3530
1+
#3540
0"
0$
0!
09
b10 :
07
b10 8
b0 4
05
b10 6
0+
#3550
1+
#3552
1#
b10001 >
b1 4
11
#3560
0+
#3570
1+
#3580
0+
#3590
1+
#3600
0+
#3602
0#
b10010 >
1/
b0 4
01
