AlteraClock/Counters.v
`include "AlteraClock/FFJK.v"

/* module Counter4Bit(
    input up_i,
    input down_i,
    input clk_i,
    input nreset_i,
    input [3:0] limit_i,

    output [3:0] count_o,
    output carryup_o, // 1 if count == limit and up = 1
    output carrydown_o // 1 if count == 0000 and down = 1
    );

    wire [3:0] toggle;
    wire islim;
    wire iszero;
    
    assign islim = (count_o == limit_i);
    assign iszero = (count_o == 4'b0000);

    assign carryup_o = islim & up_i;
    assign carrydown_o = iszero & down_i & ~up_i;

    assign toggle[0] = 1;
    FFJK FirstBit(
        .j_i(up_i & ~islim & toggle[0] | ~up_i & down_i & ~iszero & toggle[0] | ~up_i & down_i & ~islim & iszero & limit_i[0]),
        .k_i(islim & iszero | up_i & islim | up_i & ~islim & toggle[0] | ~up_i & down_i & ~iszero & toggle[0] | ~up_i & down_i & ~islim & iszero & ~limit_i[0]),
        .nreset_i(nreset_i),
        .enable_i(clk_i),
        .q_o(count_o[0])
    );

    assign toggle[1] = toggle[0] & (count_o[0] & up_i | ~count_o[0] & down_i & ~up_i);
    FFJK SecondBit(
        .j_i(up_i & ~islim & toggle[1] | ~up_i & down_i & ~iszero & toggle[1] | ~up_i & down_i & ~islim & iszero & limit_i[1]),
        .k_i(islim & iszero | up_i & islim | up_i & ~islim & toggle[1] | ~up_i & down_i & ~iszero & toggle[1] | ~up_i & down_i & ~islim & iszero & ~limit_i[1]),
        .nreset_i(nreset_i), 
        .enable_i(clk_i),
        .q_o(count_o[1])
    );

    assign toggle[2] = toggle[1] & (count_o[1] & up_i | ~count_o[1] & down_i & ~up_i);
    FFJK ThirdBit(
        .j_i(up_i & ~islim & toggle[2] | ~up_i & down_i & ~iszero & toggle[2] | ~up_i & down_i & ~islim & iszero & limit_i[2]),
        .k_i(islim & iszero | up_i & islim | up_i & ~islim & toggle[2] | ~up_i & down_i & ~iszero & toggle[2] | ~up_i & down_i & ~islim & iszero & ~limit_i[2]),
        .nreset_i(nreset_i),
        .enable_i(clk_i),
        .q_o(count_o[2])
    );

    assign toggle[3] = toggle[2] & (count_o[2] & up_i | ~count_o[2] & down_i & ~up_i);
    FFJK FourthBit(
        .j_i(up_i & ~islim & toggle[3] | ~up_i & down_i & ~iszero & toggle[3] | ~up_i & down_i & ~islim & iszero & limit_i[3]),
        .k_i(islim & iszero | up_i & islim | up_i & ~islim & toggle[3] | ~up_i & down_i & ~iszero & toggle[3] | ~up_i & down_i & ~islim & iszero & ~limit_i[3]),
        .nreset_i(nreset_i),
        .enable_i(clk_i),
        .q_o(count_o[3])
    );

endmodule */

module Counter4Bit(
    input up_i,
    input down_i, // counts up if both up/down inputs are 1
    input counter_clk_i,
    input counter_nreset_i,
    input [3:0] limit_i,

    output [3:0] count_o,
    output islim_o,
    output iszero_o
    );

    wire [3:0] toggle;
    
    assign islim_o = (count_o == limit_i);
    assign iszero_o = (count_o == 4'b0000);


    genvar i;
    generate 
        for (i = 0; i < 4; i = i + 1) begin: JKFFArray
            assign toggle[i] = (i == 0? 1'b1 : toggle[i-1] & (count_o[i-1] & up_i | ~count_o[i-1] & down_i & ~up_i));
            FFJK JKFFInst(
                .j_i(up_i & ~islim_o & toggle[i] | ~up_i & down_i & ~iszero_o & toggle[i] | ~up_i & down_i & ~islim_o & iszero_o & limit_i[i]),
                .k_i(islim_o & iszero_o | up_i & islim_o | up_i & ~islim_o & toggle[i] | ~up_i & down_i & ~iszero_o & toggle[i] | ~up_i & down_i & ~islim_o & iszero_o & ~limit_i[i]),
                .nreset_i(counter_nreset_i),
                .enable_i(counter_clk_i),
                .q_o(count_o[i])
            );
        end
    endgenerate
endmodule

module DualBCDCounter(
    input dd_up_i,
    input dd_down_i, // counts up if both up/down inputs are 1
    input dd_clk_i,
    input dd_nreset_i,
    input [3:0] tens_limit_i, // if we want this thing to count from 0 to 23, then we input tens_limit_i a 2, and ones_limit_i a 3.
    input [3:0] ones_limit_i, // ones digit will only count up to 9 even if a greater limit is fed into this input
    // Tens digit can count higher than 9, if the given limit is higher than 9. 
    
    output [3:0] tens_count_o,
    output [3:0] ones_count_o, 
    output dd_carryup_o,
    output dd_carrydown_o
    );

    reg [3:0] ones_real_limit;
    wire ones_carryup, ones_carrydown;
    wire tens_islim, tens_iszero, ones_islim, ones_iszero;

    always @(*) begin
        if (tens_limit_i == 4'b0000) ones_real_limit <= ones_limit_i;
        else begin
            if (tens_islim & dd_up_i) // if ten is at limit and we are counting up. i.e. If inteded limit is 24 and we are counting 20, 21, 22...
                ones_real_limit <= ones_limit_i;
            else if (tens_iszero & ones_iszero & dd_down_i & ~dd_up_i) // if current count is at 00 and we are counting down. 
                ones_real_limit <= ones_limit_i;
            else ones_real_limit <= 4'b1001;
        end
    end

    assign ones_carryup = ones_islim & dd_up_i;
    assign ones_carrydown = ones_iszero & dd_down_i & ~dd_up_i;

    assign dd_carryup_o = tens_islim & ones_carryup;
    assign dd_carrydown_o = tens_iszero & ones_carrydown & ~ones_carryup;
    
    
    Counter4Bit OnesDigit(
        .up_i(dd_up_i),
        .down_i(dd_down_i),
        .counter_clk_i(dd_clk_i),
        .counter_nreset_i(dd_nreset_i),
        .limit_i(ones_real_limit),
        
        .count_o(ones_count_o),
        .islim_o(ones_islim),
        .iszero_o(ones_iszero)
    );

    Counter4Bit TensDigit(
        .up_i(ones_carryup),
        .down_i(ones_carrydown),
        .counter_clk_i(dd_clk_i),
        .counter_nreset_i(dd_nreset_i),
        .limit_i(tens_limit_i),

        .count_o(tens_count_o),
        .islim_o(tens_islim),
        .iszero_o(tens_iszero)
    );
endmodule

/* module Counter3Bit(
    input up_i,
    input down_i,
    input clk_i,
    input nreset_i,
    input [2:0] limit_i,

    output [2:0] count_o,
    output islim_o, // 1 if count == limit
    output iszero_o // 1 if count == 0000
    );

endmodule

module Counter2Bit(
    input up_i,
    input down_i,
    input clk_i,
    input nreset_i,
    input [1:0] limit_i,

    output [1:0] count_o,
    output islim_o, // 1 if count == limit
    output iszero_o // 1 if count == 0000
    );

endmodule

module FiftyNineCounter(
    input up59_i,
    input down59_i,
    input clk59_i,
    input nreset59_i,

    output [3:0] ones_digit59_o,
    output [2:0] tens_digit59_o,
    output carryup_o,
    output carrydown_o
    );

    wire ones_digit_iszero, ones_digit_isnine;
    wire tens_digit_iszero, tens_digit_isfive;

    assign carryup_o = up59_i & ones_digit_isnine & tens_digit_isfive;
    assign carrydown_o = down59_i & ones_digit_iszero & ones_digit_iszero;

    Counter4Bit OnesDigit(
        .up_i(up59_i),
        .down_i(down59_i),
        .clk_i(clk59_i),
        .nreset_i(nreset59_i),
        .limit_i(4'b1001),

        .count_o(ones_digit59_o),
        .islim_o(ones_digit_isnine),
        .iszero_o(ones_digit_iszero)
    );

    Counter3Bit TensDigit(
        .up_i(up59_i & ones_digit_isnine),
        .down_i(down59_i & ones_digit_iszero),
        .clk_i(clk59_i),
        .nreset_i(nreset59_i),
        .limit_i(3'b101),

        .count_o(tens_digit59_o),
        .islim_o(tens_digit_isfive),
        .iszero_o(tens_digit_iszero)
    );

endmodule

module NinetyNineCounter(
    input up99_i,
    input down99_i,
    input clk99_i,
    input nreset99_i,

    output [3:0] ones_digit99_o,
    output [3:0] tens_digit99_o,
    output carryup_o,
    output carrydown_o
    );

    wire ones_digit_iszero, ones_digit_isnine;
    wire tens_digit_iszero, tens_digit_isnine;

    assign carryup_o = up99_i & ones_digit_isnine & tens_digit_isnine;
    assign carrydown_o = down99_i & ones_digit_iszero & ones_digit_iszero;

    Counter4Bit OnesDigit(
        .up_i(up99_i),
        .down_i(down99_i),
        .clk_i(clk99_i),
        .nreset_i(nreset99_i),
        .limit_i(4'b1001),

        .count_o(ones_digit99_o),
        .islim_o(ones_digit_isnine),
        .iszero_o(ones_digit_iszero)
    );

    Counter4Bit TensDigit(
        .up_i(up99_i & ones_digit_isnine),
        .down_i(down99_i & ones_digit_iszero),
        .clk_i(clk99_i),
        .nreset_i(nreset99_i),
        .limit_i(4'b0101),

        .count_o(tens_digit99_o),
        .islim_o(tens_digit_isnine),
        .iszero_o(tens_digit_iszero)
    );

endmodule

module TwentyThreeCounter(
    input up23_i,
    input down23_i,
    input clk23_i,
    input nreset23_i,
    
    output reg [3:0] ones_digit23_o,
    output reg [1:0] tens_digit23_o
    );

    always @(posedge clk23_i or negedge nreset23_i) begin
        if (up23_i) begin
            if (tens_digit23_o == 2'b10) begin
                if (ones_digit23_o == 4'b0011) begin
                    ones_digit23_o <= 4'b0000;
                    tens_digit23_o <= 2'b00;
                end
                else begin
                    ones_digit23_o <= ones_digit23_o + 1;
                    tens_digit23_o <= tens_digit23_o;
                end
            end
            else begin
                if (ones_digit23_o == 4'b1001) begin
                    ones_digit23_o <= 4'b0000;
                    tens_digit23_o <= tens_digit23_o + 1;
                end
                else begin
                    ones_digit23_o <= ones_digit23_o + 1;
                    tens_digit23_o <= tens_digit23_o;
                end
            end
        end
        else if (down23_i) begin
            if (ones_digit23_o == 4'b0000) begin
                if (tens_digit23_o == 2'b00) begin
                    ones_digit23_o <= 4'b0011;
                    tens_digit23_o <= 2'b10;
                end
                else begin
                    ones_digit23_o <= 4'b1001;
                    tens_digit23_o <= tens_digit23_o - 1;
                end
            end
            else begin
                ones_digit23_o <= ones_digit23_o - 1;
                tens_digit23_o <= tens_digit23_o;
            end
        end
        else begin
            ones_digit23_o <= ones_digit23_o;
            tens_digit23_o <= tens_digit23_o;
        end

    end

endmodule */

AlteraClock/TimerModule.v
`include "AlteraClock/Counters.v"

module TimerController(
    // button and switch inputs
    input set_runorpause_switch_i, // when switch is 1, it is set mode, when switch is 0, it is run/pause mode. similar to the clock module
    input up_i,
    input down_reset_i,
    input setmode_runpause_i,
    
    // timer innner control signals
    input everything_iszero_i,

    // clk and asynch (master) reset
    input clk_i,
    input nreset_i,

    // timer control outputs
    output run_o,
    output manual_up_o,
    output manual_down_o,
    output notset_any_o,
    output set_sec_o,
    output set_min_o,
    output set_hr_o,
    output counters_nreset_o,
    output end_reached_o
    );
    
    reg [2:0] control_state;
    localparam initial_state = 3'b000;
    localparam pause_state = 3'b001;
    localparam run_state = 3'b010;
    localparam end_state = 3'b011;
    localparam set_sec_state = 3'b101;
    localparam set_min_state = 3'b110;
    localparam set_hr_state = 3'b111;

    always @(posedge clk_i or negedge nreset_i) begin
        if (~nreset_i) control_state <= initial_state;
        else begin
            case (control_state) 
                initial_state: begin
                    if (set_runorpause_switch_i) control_state <= set_sec_state; // switch == 1, others: x
                    else control_state <= initial_state; // switch == 1, others: x
                end

                pause_state: begin
                    if (set_runorpause_switch_i) control_state <= set_sec_state; // switch == 1, others: x
                    else if (down_reset_i | everything_iszero_i) control_state <= initial_state; // switch == 0, down_reset or everything_iszero == 1, others: x
                    else if (setmode_runpause_i) control_state <= run_state; // switch == 0, down_reset == 0, everything_iszero == 0, setmode_runpause_i == 1, others: x
                    else control_state <= pause_state; // switch == 0, down_reset == 0, everything_zero == 0, setmode_runpause == 0, others: x
                end

                end_state: begin
                    if (set_runorpause_switch_i) control_state <= set_sec_state; // switch == 1, others: x
                    else if (up_i | down_reset_i | setmode_runpause_i) control_state <= initial_state; // switch == 0, any button == 1, others : 0
                    else control_state <= end_state; // switch == 0, all buttons : 0
                end

                run_state: begin
                    if (set_runorpause_switch_i) control_state <= set_sec_state; // switch == 1, others: x
                    else if (down_reset_i | everything_iszero_i) control_state <= initial_state; // switch == 0, down_reset or everything_iszero == 1, others: x
                    else if (setmode_runpause_i) control_state <= pause_state; // switch == 0, everything_iszero == 0, down_reset == 0, setmode_runpause == 1, others: x
                    else control_state <= run_state; // switch == 0, everything_iszero ==0, down_reset == 0, setmode_runpause == 0, others: x;
                end

                set_sec_state: begin
                    if (~set_runorpause_switch_i) begin
                        if (everything_iszero_i) control_state <= initial_state; // switch == 0, everything_iszero = 1, others: x
                        else control_state <= pause_state; // switch == 0, everything_iszero = 0, others: x
                    end
                    else if (setmode_runpause_i) control_state <= set_min_state; // switch == 1, setmode_runpause == 1, others: x
                    else control_state <= set_sec_state; // switch == 1, setmode_runpause == 0, others: x
                end

                set_min_state: begin
                    if (~set_runorpause_switch_i) begin
                        if (everything_iszero_i) control_state <= initial_state; // switch == 0, everything_iszero = 1, others: x
                        else control_state <= pause_state; // switch == 0, everything_iszero = 0, others: x
                    end
                    else if (setmode_runpause_i) control_state <= set_hr_state; // switch == 1, setmode_runpause == 1, others: x
                    else control_state <= set_min_state; // switch == 1, setmode_runpause == 0, others: x
                end

                set_hr_state: begin
                    if (~set_runorpause_switch_i) begin
                        if (everything_iszero_i) control_state <= initial_state; // switch == 0, everything_iszero = 1, others: x
                        else control_state <= pause_state; // switch == 0, everything_iszero = 0, others: x
                    end
                    else if (setmode_runpause_i) control_state <= set_sec_state; // switch == 1, setmode_runpause == 1, others: x
                    else control_state <= set_hr_state; // switch == 1, setmode_runpause == 0, others: x
                end
                default: control_state <= initial_state;
            endcase
        end
    end

    assign run_o = (control_state == run_state);
    assign manual_up_o = control_state[2] & up_i;
    assign manual_down_o = control_state[2] & down_reset_i;
    assign notset_any_o = ~control_state[2];
    assign set_sec_o = (control_state == set_sec_state);
    assign set_min_o = (control_state == set_min_state);
    assign set_hr_o = (control_state == set_hr_state);
    assign counters_nreset_o = ~((control_state == initial_state) | (control_state == end_state));
    assign end_reached_o = (control_state == end_state);

endmodule

module TimerModule(
    // button and switch inputs
    input set_runorpause_switch_i, // when switch is 1, it is set mode, when switch is 0, it is run/pause mode. similar to the clock module
    input up_i,
    input down_reset_i,
    input setmode_runpause_i,

    input clk_i,
    input nreset_i,

    output blink_lessthansec_o,
    output blink_sec_o,
    output blink_min_o,
    output blink_hr_o,

    output [3:0] centisec_o,
    output [3:0] decisec_o,

    output [3:0] sec_o,
    output [3:0] decasec_o,

    output [3:0] min_o,
    output [3:0] decamin_o,

    output [3:0] hr_o,
    output [3:0] decahr_o
    );

    wire run;
    wire manual_up;
    wire manual_down;
    wire notset_any;
    wire set_sec;
    wire set_min;
    wire set_hr;
    wire counters_nreset;
    wire end_reached;

    wire everything_iszero;
    assign everything_iszero = ({centisec_o, decisec_o, sec_o, decasec_o, min_o, decamin_o, hr_o, decahr_o} == 32'b0);

    TimerController Controller(
        // button and switch inputs
        .set_runorpause_switch_i(set_runorpause_switch_i), // when switch is 1, it is set mode, when switch is 0, it is run/pause mode. similar to the clock module
        .up_i(up_i),
        .down_reset_i(down_reset_i),
        .setmode_runpause_i(setmode_runpause_i),
        
        // timer innner control signals
        .everything_iszero_i(everything_iszero_i),

        // clk and asynch (master) reset
        .clk_i(clk_i),
        .nreset_i(nreset_i),

        // timer control outputs
        .run_o(run),
        .manual_up_o(manual_up),
        .manual_down_o(manual_down),
        .notset_any_o(notset_any),
        .set_sec_o(set_sec),
        .set_min_o(set_min),
        .set_hr_o(set_hr),
        .counters_nreset_o(counters_nreset),
        .end_reached_o(end_reached)
    );

    wire lessthansec_borrow;
    DualBCDCounter LessThanSecCounter(
        .dd_up_i(1'b0),
        .dd_down_i(run),
        .dd_clk_i(clk_i),
        .dd_nreset_i(counters_nreset & notset_any),
        .tens_limit_i(4'b1001),
        .ones_limit_i(4'b1001),
        
        .tens_count_o(decisec_o),
        .ones_count_o(centisec_o),
        .dd_carryup_o(),
        .dd_carrydown_o(lessthansec_borrow)
    );

    wire sec_borrow;
    DualBCDCounter SecCounter(
        .dd_up_i(set_sec & manual_up),
        .dd_down_i(run & lessthansec_borrow | set_sec & manual_down),
        .dd_clk_i(clk_i),
        .dd_nreset_i(counters_nreset),
        .tens_limit_i(4'b0101),
        .ones_limit_i(4'b1001),
        
        .tens_count_o(decasec_o),
        .ones_count_o(sec_o),
        .dd_carryup_o(),
        .dd_carrydown_o(sec_borrow)
    );

    wire min_borrow;
    DualBCDCounter MinCounter(
        .dd_up_i(set_min & manual_up),
        .dd_down_i(run & sec_borrow | set_min & manual_down),
        .dd_clk_i(clk_i),
        .dd_nreset_i(counters_nreset),
        .tens_limit_i(4'b0101),
        .ones_limit_i(4'b1001),
        
        .tens_count_o(decamin_o),
        .ones_count_o(min_o),
        .dd_carryup_o(),
        .dd_carrydown_o(min_borrow)
    );

    DualBCDCounter HrCounter(
        .dd_up_i(set_hr & manual_up),
        .dd_down_i(run & min_borrow | set_hr & manual_down),
        .dd_clk_i(clk_i),
        .dd_nreset_i(counters_nreset),
        .tens_limit_i(4'b1001),
        .ones_limit_i(4'b1001),
        
        .tens_count_o(decahr_o),
        .ones_count_o(hr_o),
        .dd_carryup_o(),
        .dd_carrydown_o()
    );

    assign blink_lessthansec_o = end_reached;
    assign blink_sec_o = end_reached | set_sec;
    assign blink_min_o = end_reached | set_min;
    assign blink_hr_o = end_reached | set_hr;
endmodule

AlteraClock/tb_TimerController.v
`include "AlteraClock/TimerModule.v"
`timescale 1ns/1ns

module tb_TimerController();

    reg [3:0] buttons_simulation;

    reg tb_set_runorpause_switch; 
    reg tb_up;
    reg tb_down_reset;
    reg tb_setmode_runpause;
    
    // timer innner control signals
    reg tb_everything_iszero;

    // clk and asynch (master) reset
    reg tb_clk;
    reg tb_nreset;

    wire tb_run;
    wire tb_manual_up;
    wire tb_manual_down;
    wire tb_notset_any;
    wire tb_set_sec;
    wire tb_set_min;
    wire tb_set_hr;
    wire tb_counters_nreset;
    wire tb_end_reached;

    always #10 tb_clk <= ~tb_clk;      

    TimerController TestController(
        .set_runorpause_switch_i(tb_set_runorpause_switch), 
        .up_i(tb_up),
        .down_reset_i(tb_down_reset),
        .setmode_runpause_i(tb_setmode_runpause),
        
        .everything_iszero_i(tb_everything_iszero),

        .clk_i(tb_clk),
        .nreset_i(tb_nreset),

        // timer control outputs
        .run_o(tb_run),
        .manual_up_o(tb_manual_up),
        .manual_down_o(tb_manual_down),
        .notset_any_o(tb_notset_any),
        .set_sec_o(tb_set_sec),
        .set_min_o(tb_set_min),
        .set_hr_o(tb_set_hr),
        .counters_nreset_o(tb_counters_nreset),
        .end_reached_o(tb_end_reached)
    );

    initial begin
        $dumpfile("AlteraClock/BuildFiles/tb_TimerController.vcd");
        $dumpvars(0, tb_TimerController);

        tb_set_runorpause_switch = 0; 
        tb_up = 0;
        tb_down_reset = 0;
        tb_setmode_runpause = 0;
        buttons_simulation = 4'b0;
        
        // timer innner control signals
        tb_everything_iszero = 0;

        // clk and asynch (master) reset
        tb_clk = 0;
        tb_nreset = 0;

        #1
        tb_nreset = 1;

        #19

        for (integer i = 0; i < 20; i = i + 1) begin
            {tb_set_runorpause_switch, tb_up, tb_down_reset, tb_setmode_runpause, tb_everything_iszero} <= $random;
            buttons_simulation <= buttons_simulation + 1;

            #20;

        end

        $finish;
    end
endmodule

AlteraClock/BuildFiles/tb_TimerController.vcd
$date
	Wed Apr 17 21:18:17 2024
$end
$version
	Icarus Verilog
$end
$timescale
	1ns
$end
$scope module tb_TimerController $end
$var wire 1 ! tb_set_sec $end
$var wire 1 " tb_set_min $end
$var wire 1 # tb_set_hr $end
$var wire 1 $ tb_run $end
$var wire 1 % tb_notset_any $end
$var wire 1 & tb_manual_up $end
$var wire 1 ' tb_manual_down $end
$var wire 1 ( tb_end_reached $end
$var wire 1 ) tb_counters_nreset $end
$var reg 4 * buttons_simulation [3:0] $end
$var reg 1 + tb_clk $end
$var reg 1 , tb_down_reset $end
$var reg 1 - tb_everything_iszero $end
$var reg 1 . tb_nreset $end
$var reg 1 / tb_set_runorpause_switch $end
$var reg 1 0 tb_setmode_runpause $end
$var reg 1 1 tb_up $end
$scope module TestController $end
$var wire 1 + clk_i $end
$var wire 1 ) counters_nreset_o $end
$var wire 1 , down_reset_i $end
$var wire 1 - everything_iszero_i $end
$var wire 1 ' manual_down_o $end
$var wire 1 & manual_up_o $end
$var wire 1 % notset_any_o $end
$var wire 1 . nreset_i $end
$var wire 1 / set_runorpause_switch_i $end
$var wire 1 0 setmode_runpause_i $end
$var wire 1 1 up_i $end
$var wire 1 ! set_sec_o $end
$var wire 1 " set_min_o $end
$var wire 1 # set_hr_o $end
$var wire 1 $ run_o $end
$var wire 1 ( end_reached_o $end
$var parameter 3 2 end_state $end
$var parameter 3 3 initial_state $end
$var parameter 3 4 pause_state $end
$var parameter 3 5 run_state $end
$var parameter 3 6 set_hr_state $end
$var parameter 3 7 set_min_state $end
$var parameter 3 8 set_sec_state $end
$var reg 3 9 control_state [2:0] $end
$upscope $end
$scope begin $ivl_for_loop0 $end
$var integer 32 : i [31:0] $end
$upscope $end
$upscope $end
$enddefinitions $end
$comment Show the parameter values. $end
$dumpall
b101 8
b110 7
b111 6
b10 5
b1 4
b0 3
b11 2
$end
#0
$dumpvars
bx :
b0 9
01
00
0/
0.
0-
0,
0+
b0 *
0)
0(
0'
0&
1%
0$
0#
0"
0!
$end
#1
1.
#10
1+
#20
0+
b1 *
1,
b0 :
#30
1+
#40
0+
b10 *
0,
1-
b1 :
#50
1+
#60
0+
b11 *
11
b10 :
#70
1+
#80
0+
b100 *
01
10
b11 :
#90
1+
#100
0+
b101 *
11
1,
00
b100 :
#110
1+
#120
0+
b110 *
b101 :
#130
1+
#140
0+
b111 *
01
b110 :
#150
1+
#160
0+
b1000 *
1/
0,
10
0-
b111 :
#170
0%
1)
1!
b101 9
1+
#180
0+
b1001 *
0/
00
1-
b1000 :
#190
1%
0)
0!
b0 9
1+
#200
0+
b1010 *
11
1,
b1001 :
#210
1+
#220
0+
b1011 *
1/
01
10
0-
b1010 :
#230
1'
0%
1)
1!
b101 9
1+
#240
1&
0+
b1100 *
11
00
1-
b1011 :
#250
1+
#260
0+
b1101 *
0/
b1100 :
#270
0&
0'
1%
0)
0!
b0 9
1+
#280
0+
b1110 *
0-
b1101 :
#290
1+
#300
0+
b1111 *
1/
0,
1-
b1110 :
#310
1&
0%
1)
1!
b101 9
1+
#320
0&
1'
0+
b0 *
0/
01
1,
10
0-
b1111 :
#330
0'
1%
0!
b1 9
1+
#340
0+
b1 *
00
1-
b10000 :
#350
0)
b0 9
1+
#360
0+
b10 *
11
0,
10
0-
b10001 :
#370
1+
#380
0+
b11 *
01
1,
00
1-
b10010 :
#390
1+
#400
0+
b100 *
1/
10
b10011 :
#410
1'
0%
1)
1!
b101 9
1+
#420
0+
b10100 :
